{
  "screenName": "MonitoringScreen",
  "sourceScreenshot": "04-monitoring.png",
  "layout": {
    "type": "shell-with-single-panel",
    "panel": "system-audit-trail"
  },
  "components": [
    "ScreenShell",
    "AuditTrailPanel",
    "LogRow",
    "SeverityBadge"
  ],
  "tokenRefs": {
    "colors": [
      "Surface Layers.Surface 0",
      "Surface Layers.Surface 1",
      "Border Tokens.default",
      "Semantic Colors.Info",
      "Semantic Colors.Warning",
      "Semantic Colors.Error",
      "Quality Gate States.Not Started"
    ],
    "typography": ["Heading MD", "Body MD", "Caption", "Overline"],
    "spacing": ["1", "2", "3", "4", "5", "6"],
    "radii": ["11", "7"]
  },
  "states": ["default", "loading", "empty-log", "error"],
  "interactions": ["log-row-focus", "panel-scroll"],
  "assets": [],
  "todos": [
    "Connect stream mode to runtime log source."
  ]
}
